pymailscraper/__init__.py
pymailscraper/cli.py
pymailscraper/scraper.py
pymailscraper-0.1.0.dist-info/LICENSE
pymailscraper-0.1.0.dist-info/METADATA
pymailscraper-0.1.0.dist-info/WHEEL
pymailscraper-0.1.0.dist-info/entry_points.txt
pymailscraper-0.1.0.dist-info/top_level.txt
pymailscraper-0.1.0.dist-info/RECORD
