Metadata-Version: 2.1
Name: pymailscraper
Version: 0.1.0
Summary: A Python tool for scraping email addresses from websites
Home-page: https://github.com/mmikhan/pymailscraper
Author: Md Mazedul Islam Khan
Author-email: mazedulislamkhan@gmail.com
Classifier: Programming Language :: Python :: 3
Classifier: License :: OSI Approved :: MIT License
Classifier: Operating System :: OS Independent
Requires-Python: >=3.6
License-File: LICENSE
Requires-Dist: requests
Requires-Dist: beautifulsoup4
Requires-Dist: tqdm
